meersolar/__init__.py
meersolar/crystalball/__init__.py
meersolar/crystalball/budget.py
meersolar/crystalball/crystalball.py
meersolar/crystalball/filtering.py
meersolar/crystalball/logger_init.py
meersolar/crystalball/ms.py
meersolar/crystalball/region.py
meersolar/crystalball/wsclean.py
meersolar/data/__init__.py
meersolar/data/sendmail.so
meersolar/meerpipeline/__init__.py
meersolar/meerpipeline/basic_cal.py
meersolar/meerpipeline/do_apply_basiccal.py
meersolar/meerpipeline/do_apply_selfcal.py
meersolar/meerpipeline/do_fluxcal.py
meersolar/meerpipeline/do_imaging.py
meersolar/meerpipeline/do_partition.py
meersolar/meerpipeline/do_selfcal.py
meersolar/meerpipeline/do_sidereal_cor.py
meersolar/meerpipeline/do_target_split.py
meersolar/meerpipeline/flagging.py
meersolar/meerpipeline/import_model.py
meersolar/meerpipeline/init_data.py
meersolar/meerpipeline/kill_job.py
meersolar/meerpipeline/master_flow.py
meersolar/meerpipeline/meer_make_ds.py
meersolar/meerpipeline/meer_pbcor.py
meersolar/meerpipeline/prefect_server.py
meersolar/meerpipeline/show_msdetails.py
meersolar/meerpipeline/show_status.py
meersolar/meerpipeline/single_image_meerpbcor.py
meersolar/meerpipeline/viewer.py
meersolar/utils/__init__.py
meersolar/utils/basic_utils.py
meersolar/utils/calibration.py
meersolar/utils/casatasks.py
meersolar/utils/flagging.py
meersolar/utils/image_utils.py
meersolar/utils/imaging.py
meersolar/utils/logger_utils.py
meersolar/utils/meer_ploting_utils.py
meersolar/utils/meer_utils.py
meersolar/utils/ms_metadata.py
meersolar/utils/prefect_logger_utils.py
meersolar/utils/prefect_setup_utils.py
meersolar/utils/proc_manage_utils.py
meersolar/utils/resource_utils.py
meersolar/utils/selfcal_utils.py
meersolar/utils/sunpos_utils.py
meersolar/utils/udocker_utils.py
meersolar-3.0.1.dist-info/licenses/LICENSE
meersolar-3.0.1.dist-info/METADATA
meersolar-3.0.1.dist-info/WHEEL
meersolar-3.0.1.dist-info/entry_points.txt
meersolar-3.0.1.dist-info/top_level.txt
meersolar-3.0.1.dist-info/RECORD
